[
  {
    "id": 0,
    "title": "크림소스 입고 안내",
    "created_datetime": "",
    "content": "안녕하세요. 청년소스입니다.\n2023년 10월 16일 크림소스가 입고되었습니다.\n\n해당 제품은 청년소스 스마트스토어 내 확인 가능합니다.\n\n감사합니다."
  },
  {
    "id": 1,
    "title": "크림소스 입고 안내",
    "created_datetime": "",
    "content": "안녕하세요. 청년소스입니다.\n2023년 10월 16일 크림소스가 입고되었습니다.\n\n해당 제품은 청년소스 스마트스토어 내 확인 가능합니다.\n\n감사합니다."
  },
  {
    "id": 2,
    "title": "크림소스 입고 안내",
    "created_datetime": "",
    "content": "안녕하세요. 청년소스입니다.\n2023년 10월 16일 크림소스가 입고되었습니다.\n\n해당 제품은 청년소스 스마트스토어 내 확인 가능합니다.\n\n감사합니다."
  },
  {
    "id": 3,
    "title": "크림소스 입고 안내",
    "created_datetime": "",
    "content": "안녕하세요. 청년소스입니다.\n2023년 10월 16일 크림소스가 입고되었습니다.\n\n해당 제품은 청년소스 스마트스토어 내 확인 가능합니다.\n\n감사합니다."
  },
  {
    "id": 4,
    "title": "크림소스 입고 안내",
    "created_datetime": "",
    "content": "안녕하세요. 청년소스입니다.\n2023년 10월 16일 크림소스가 입고되었습니다.\n\n해당 제품은 청년소스 스마트스토어 내 확인 가능합니다.\n\n감사합니다."
  },
  {
    "id": 5,
    "title": "크림소스 입고 안내",
    "created_datetime": "",
    "content": "안녕하세요. 청년소스입니다.\n2023년 10월 16일 크림소스가 입고되었습니다.\n\n해당 제품은 청년소스 스마트스토어 내 확인 가능합니다.\n\n감사합니다."
  },
  {
    "id": 6,
    "title": "크림소스 입고 안내",
    "created_datetime": "",
    "content": "안녕하세요. 청년소스입니다.\n2023년 10월 16일 크림소스가 입고되었습니다.\n\n해당 제품은 청년소스 스마트스토어 내 확인 가능합니다.\n\n감사합니다."
  }
]
